pyesicentro/__init__.py
pyesicentro/const.py
pyesicentro/logger.py
pyesicentro/service.py
pyesicentro/thermostat.py
pyesicentro/utilities.py
pyesicentro-1.2.3.dist-info/LICENSE
pyesicentro-1.2.3.dist-info/METADATA
pyesicentro-1.2.3.dist-info/WHEEL
pyesicentro-1.2.3.dist-info/top_level.txt
pyesicentro-1.2.3.dist-info/RECORD
